README.rst
setup.py
dj_extensions/__init__.py
dj_extensions.egg-info/PKG-INFO
dj_extensions.egg-info/SOURCES.txt
dj_extensions.egg-info/dependency_links.txt
dj_extensions.egg-info/not-zip-safe
dj_extensions.egg-info/requires.txt
dj_extensions.egg-info/top_level.txt
dj_extensions/views/__init__.py
dj_extensions/views/mixins.py