Metadata-Version: 1.1
Name: dj-extensions
Version: 0.1.5.post2
Summary: Yet another Django extension with set of generic reusable, pluggable mixins
Home-page: https://github.com/jahan01/dj-extensions
Author: Jahan Balasubramaniam
Author-email: jahan.unofficial@gmail.com
License: MIT
Keywords: django views mixins
Platform: UNKNOWN
Classifier: Programming Language :: Python
Classifier: License :: OSI Approved :: MIT License
Classifier: Environment :: Web Environment
Classifier: Environment :: Plugins
Classifier: Development Status :: 5 - Production/Stable
Classifier: Programming Language :: Python :: 2.6
Classifier: Programming Language :: Python :: 2.7
Classifier: Programming Language :: Python :: 3.2
Classifier: Programming Language :: Python :: 3.3
Classifier: Programming Language :: Python :: 3.4
Classifier: Programming Language :: Python :: 3.5
Classifier: Framework :: Django
Classifier: Framework :: Django :: 1.7
Classifier: Framework :: Django :: 1.8
Classifier: Framework :: Django :: 1.9
Classifier: Topic :: Software Development :: Libraries :: Python Modules
Classifier: Topic :: Utilities
